odoo9_addon_medical_medication-9.0.1.0.1-py2.7-nspkg.pth
odoo9_addon_medical_medication-9.0.1.0.1.dist-info/top_level.txt
odoo9_addon_medical_medication-9.0.1.0.1.dist-info/WHEEL
odoo9_addon_medical_medication-9.0.1.0.1.dist-info/RECORD
odoo9_addon_medical_medication-9.0.1.0.1.dist-info/metadata.json
odoo9_addon_medical_medication-9.0.1.0.1.dist-info/DESCRIPTION.rst
odoo9_addon_medical_medication-9.0.1.0.1.dist-info/METADATA
odoo9_addon_medical_medication-9.0.1.0.1.dist-info/namespace_packages.txt
odoo_addons/medical_medication/__openerp__.py
odoo_addons/medical_medication/__init__.py
odoo_addons/medical_medication/README.rst
odoo_addons/medical_medication/security/ir.model.access.csv
odoo_addons/medical_medication/models/medical_patient.py
odoo_addons/medical_medication/models/medical_medication_dosage.py
odoo_addons/medical_medication/models/__init__.py
odoo_addons/medical_medication/models/medical_patient_medication.py
odoo_addons/medical_medication/models/medical_medication_template.py
odoo_addons/medical_medication/models/abstract_medical_medication.py
odoo_addons/medical_medication/i18n/es_CO.po
odoo_addons/medical_medication/i18n/es_ES.po
odoo_addons/medical_medication/i18n/pt_BR.po
odoo_addons/medical_medication/views/medical_medication_template_view.xml
odoo_addons/medical_medication/views/medical_patient_view.xml
odoo_addons/medical_medication/views/medical_menu.xml
odoo_addons/medical_medication/views/medical_medication_dosage_view.xml
odoo_addons/medical_medication/views/medical_patient_medication_view.xml
odoo_addons/medical_medication/data/product_uom.xml
odoo_addons/medical_medication/data/medical_medication_dosage.xml
odoo_addons/medical_medication/tests/test_abstract_medical_medication.py
odoo_addons/medical_medication/tests/__init__.py
odoo_addons/medical_medication/tests/test_medical_medication_template.py
odoo_addons/medical_medication/tests/test_medical_medication_dosage.py
odoo_addons/medical_medication/demo/medical_medicament_demo.xml
odoo_addons/medical_medication/demo/medical_patient_demo.xml
odoo_addons/medical_medication/demo/medical_pathology_demo.xml
odoo_addons/medical_medication/demo/medical_patient_medication_demo.xml
odoo_addons/medical_medication/static/description/icon.png
