Metadata-Version: 2.0
Name: odoo9-addon-medical-medication
Version: 9.0.1.0.1
Summary: Introduce medication notion into the medical addons.
Home-page: http://www.acsone.eu
Author: LasLabs, ACSONE SA/NV, Odoo Community Association (OCA)
Author-email: support@odoo-community.org
License: LGPL-3
Platform: UNKNOWN
Requires-Dist: odoo (<9.1a,>=9.0a)
Requires-Dist: odoo9-addon-medical-medicament
Requires-Dist: odoo9-addon-medical-patient-disease
Classifier: Programming Language :: Python :: 2.7
Classifier: Framework :: Odoo
Classifier: License :: OSI Approved :: GNU Lesser General Public License v3 (LGPLv3)
